setup.py
myPreProcess/__init__.py
myPreProcess/_core.py
myPreProcess.egg-info/PKG-INFO
myPreProcess.egg-info/SOURCES.txt
myPreProcess.egg-info/dependency_links.txt
myPreProcess.egg-info/top_level.txt