Metadata-Version: 2.1
Name: myPreProcess
Version: 0.0.1
Summary: hhh
Home-page: https://github.com/
Author: xc
Author-email: 2675245204@qq.com
License: UNKNOWN
Platform: UNKNOWN
Classifier: Programming Language :: Python :: 3
Classifier: License :: OSI Approved :: MIT License
Classifier: Operating System :: OS Independent
